<?xml version="1.0" encoding="utf-8" ?>
<dwsync>
<file name="index.html" server="afsconnect1.njit.edu//afs/cad.njit.edu/u/r/v/rvz2/public_html/" local="131858553192945430" remote="131858449570000000" Dst="1" />
<file name="instructor.html" server="afsconnect1.njit.edu//afs/cad.njit.edu/u/r/v/rvz2/public_html/" local="131858562282089310" remote="131858451300000000" Dst="1" />
<file name="instructor.js" server="afsconnect1.njit.edu//afs/cad.njit.edu/u/r/v/rvz2/public_html/" local="131866445947127658" remote="131866334980000000" Dst="1" />
<file name="instructorAddQ.php" server="afsconnect1.njit.edu//afs/cad.njit.edu/u/r/v/rvz2/public_html/" local="131866397986229897" remote="131866288420000000" Dst="1" />
<file name="instructorCreateE.php" server="afsconnect1.njit.edu//afs/cad.njit.edu/u/r/v/rvz2/public_html/" local="131849807220321903" remote="131849735370000000" Dst="1" />
<file name="instructorReleaseExam.php" server="afsconnect1.njit.edu//afs/cad.njit.edu/u/r/v/rvz2/public_html/" local="131856690857071623" remote="131856616040000000" Dst="1" />
<file name="instructorReleaseGrade.php" server="afsconnect1.njit.edu//afs/cad.njit.edu/u/r/v/rvz2/public_html/" local="131859287131249233" remote="131859176620000000" Dst="1" />
<file name="instructorShowQ.php" server="afsconnect1.njit.edu//afs/cad.njit.edu/u/r/v/rvz2/public_html/" local="131849807221631150" remote="131849735370000000" Dst="1" />
<file name="instructorSubmitExam.php" server="afsconnect1.njit.edu//afs/cad.njit.edu/u/r/v/rvz2/public_html/" local="131858519716052646" remote="131858416180000000" Dst="1" />
<file name="instructorSubmitGraded.php" server="afsconnect1.njit.edu//afs/cad.njit.edu/u/r/v/rvz2/public_html/" local="131866407370397994" remote="131866296460000000" Dst="1" />
<file name="instructorSubmitRelease.php" server="afsconnect1.njit.edu//afs/cad.njit.edu/u/r/v/rvz2/public_html/" local="131855964479590136" remote="131855889540000000" Dst="1" />
<file name="login.php" server="afsconnect1.njit.edu//afs/cad.njit.edu/u/r/v/rvz2/public_html/" local="131858615570760266" remote="131858504900000000" Dst="1" />
<file name="main.css" server="afsconnect1.njit.edu//afs/cad.njit.edu/u/r/v/rvz2/public_html/" local="131849807224079747" remote="131849735380000000" Dst="1" />
<file name="myscript.js" server="afsconnect1.njit.edu//afs/cad.njit.edu/u/r/v/rvz2/public_html/" local="131849807224619251" remote="131849735380000000" Dst="1" />
<file name="README.md" server="afsconnect1.njit.edu//afs/cad.njit.edu/u/r/v/rvz2/public_html/" local="131849806032391170" remote="131849735380000000" Dst="1" />
<file name="student1.html" server="afsconnect1.njit.edu//afs/cad.njit.edu/u/r/v/rvz2/public_html/" local="131856670000774627" remote="131856616040000000" Dst="1" />
<file name="student1.js" server="afsconnect1.njit.edu//afs/cad.njit.edu/u/r/v/rvz2/public_html/" local="131866438475576341" remote="131866327370000000" Dst="1" />
<file name="student1GetExams.php" server="afsconnect1.njit.edu//afs/cad.njit.edu/u/r/v/rvz2/public_html/" local="131849807280165437" remote="131849735380000000" Dst="1" />
<file name="student1GetGrades.php" server="afsconnect1.njit.edu//afs/cad.njit.edu/u/r/v/rvz2/public_html/" local="131862702319663320" remote="131862617600000000" Dst="1" />
<file name="student1RequestExamToTake.php" server="afsconnect1.njit.edu//afs/cad.njit.edu/u/r/v/rvz2/public_html/" local="131861919979303538" remote="131861809020000000" Dst="1" />
<file name="student1SubmitExamAnswers.php" server="afsconnect1.njit.edu//afs/cad.njit.edu/u/r/v/rvz2/public_html/" local="131861925320450590" remote="131861814280000000" Dst="1" />
<file name="student2.html" server="afsconnect1.njit.edu//afs/cad.njit.edu/u/r/v/rvz2/public_html/" local="131858552572099068" remote="131858449580000000" Dst="1" />
<file name="student2.js" server="afsconnect1.njit.edu//afs/cad.njit.edu/u/r/v/rvz2/public_html/" local="131858560385441335" remote="131858449580000000" Dst="1" />
<file name="student2GetExams.php" server="afsconnect1.njit.edu//afs/cad.njit.edu/u/r/v/rvz2/public_html/" local="131849807284823093" remote="131849735390000000" Dst="1" />
<file name="student2GetGrades.php" server="afsconnect1.njit.edu//afs/cad.njit.edu/u/r/v/rvz2/public_html/" local="131849807285592662" remote="131849735390000000" Dst="1" />
<file name="student2RequestExamToTake.php" server="afsconnect1.njit.edu//afs/cad.njit.edu/u/r/v/rvz2/public_html/" local="131849807286242283" remote="131849735390000000" Dst="1" />
<file name="student2SubmitExamAnswers.php" server="afsconnect1.njit.edu//afs/cad.njit.edu/u/r/v/rvz2/public_html/" local="131858615715563868" remote="131858504910000000" Dst="1" />
<file name="instructorViewGradedExam.php" server="afsconnect1.njit.edu//afs/cad.njit.edu/u/r/v/rvz2/public_html/" local="131866277144644209" remote="131866166470000000" Dst="1" />
<file name="student1ViewReport.php" server="afsconnect1.njit.edu//afs/cad.njit.edu/u/r/v/rvz2/public_html/" local="131862734774425520" remote="131862634510000000" Dst="1" />
<file name="instructorDeleteQ.php" server="afsconnect1.njit.edu//afs/cad.njit.edu/u/r/v/rvz2/public_html/" local="131862952744650252" remote="131862852090000000" Dst="1" />
</dwsync>